LICENSE
MANIFEST.in
README.md
setup.py
django_hashbrown.egg-info/PKG-INFO
django_hashbrown.egg-info/SOURCES.txt
django_hashbrown.egg-info/dependency_links.txt
django_hashbrown.egg-info/not-zip-safe
django_hashbrown.egg-info/top_level.txt
hashbrown/__init__.py
hashbrown/admin.py
hashbrown/compat.py
hashbrown/models.py
hashbrown/tests.py
hashbrown/testutils.py
hashbrown/utils.py
hashbrown/management/__init__.py
hashbrown/management/commands/__init__.py
hashbrown/management/commands/switches.py
hashbrown/templatetags/__init__.py
hashbrown/templatetags/hashbrown_tags.py