Metadata-Version: 1.1
Name: django-hashbrown
Version: 0.6.1
Summary: Yet another dead simple feature switching library for Django.
Home-page: https://github.com/potatolondon/django-hashbrown
Author: Pablo Recio
Author-email: pablo@potatolondon.com
License: BSD
Keywords: django feature switching potato
Platform: UNKNOWN
Classifier: Development Status :: 4 - Beta
Classifier: Framework :: Django
Classifier: Intended Audience :: Developers
Classifier: License :: OSI Approved :: BSD License
Classifier: Operating System :: OS Independent
Classifier: Programming Language :: Python
